{
  "Id": "f6ab795d-93d7-42d7-b987-d9834ed955b9",
  "Name": "DocumentFile",
  "OriginalName": "DocumentFile",
  "NamePlural": "DocumentFiles",
  "DatabaseTableName": "DocumentFiles",
  "Namespace": "DocumentFiles",
  "Type": 1,
  "MasterEntityName": null,
  "MasterEntity": null,
  "BaseClass": "FullAuditedAggregateRoot",
  "PageTitle": "DocumentFiles",
  "MenuIcon": "file-alt",
  "PrimaryKeyType": "Guid",
  "PreserveCustomCode": true,
  "IsMultiTenant": true,
  "CheckConcurrency": true,
  "BulkDeleteEnabled": true,
  "ShouldCreateUserInterface": true,
  "ShouldCreateBackend": true,
  "ShouldExportExcel": true,
  "ShouldAddMigration": true,
  "ShouldUpdateDatabase": true,
  "CreateTests": true,
  "Properties": [
    {
      "Id": "3b94bb22-be1f-4f39-aee4-ba1ca7c4b800",
      "Name": "Name",
      "Type": "string",
      "EnumType": "",
      "EnumNamespace": "",
      "EnumAngularImport": "shared/enums",
      "EnumFilePath": null,
      "DefaultValue": null,
      "IsNullable": false,
      "IsRequired": true,
      "IsFilterable": true,
      "AllowEmptyStrings": false,
      "IsTextArea": false,
      "MinLength": null,
      "MaxLength": null,
      "SortOrder": 0,
      "SortType": 0,
      "Regex": "",
      "EmailValidation": false,
      "ShowOnList": true,
      "ShowOnCreateModal": true,
      "ShowOnEditModal": true,
      "ReadonlyOnEditModal": false,
      "EnumValues": null,
      "IsSelected": true,
      "MaxFileSize": null,
      "OrdinalIndex": 0
    },
    {
      "Id": "f2564e22-3722-4c05-aee9-c51cf2f0cefe",
      "Name": "Path",
      "Type": "string",
      "EnumType": "",
      "EnumNamespace": "",
      "EnumAngularImport": "shared/enums",
      "EnumFilePath": null,
      "DefaultValue": null,
      "IsNullable": false,
      "IsRequired": false,
      "IsFilterable": true,
      "AllowEmptyStrings": false,
      "IsTextArea": false,
      "MinLength": null,
      "MaxLength": null,
      "SortOrder": 0,
      "SortType": 0,
      "Regex": "",
      "EmailValidation": false,
      "ShowOnList": true,
      "ShowOnCreateModal": true,
      "ShowOnEditModal": true,
      "ReadonlyOnEditModal": false,
      "EnumValues": null,
      "IsSelected": true,
      "MaxFileSize": null,
      "OrdinalIndex": 0
    },
    {
      "Id": "ec5935d1-54a7-4500-bb9b-1c6fa71273d1",
      "Name": "Hash",
      "Type": "string",
      "EnumType": "",
      "EnumNamespace": "",
      "EnumAngularImport": "shared/enums",
      "EnumFilePath": null,
      "DefaultValue": null,
      "IsNullable": false,
      "IsRequired": false,
      "IsFilterable": true,
      "AllowEmptyStrings": false,
      "IsTextArea": false,
      "MinLength": null,
      "MaxLength": null,
      "SortOrder": 0,
      "SortType": 0,
      "Regex": "",
      "EmailValidation": false,
      "ShowOnList": true,
      "ShowOnCreateModal": true,
      "ShowOnEditModal": true,
      "ReadonlyOnEditModal": false,
      "EnumValues": null,
      "IsSelected": true,
      "MaxFileSize": null,
      "OrdinalIndex": 0
    },
    {
      "Id": "eabf360e-47c2-42ef-a891-af2b3133441e",
      "Name": "IsSigned",
      "Type": "bool",
      "EnumType": "",
      "EnumNamespace": "",
      "EnumAngularImport": "shared/enums",
      "EnumFilePath": null,
      "DefaultValue": "false",
      "IsNullable": false,
      "IsRequired": false,
      "IsFilterable": true,
      "AllowEmptyStrings": false,
      "IsTextArea": false,
      "MinLength": null,
      "MaxLength": null,
      "SortOrder": 0,
      "SortType": 0,
      "Regex": "",
      "EmailValidation": false,
      "ShowOnList": true,
      "ShowOnCreateModal": true,
      "ShowOnEditModal": true,
      "ReadonlyOnEditModal": false,
      "EnumValues": null,
      "IsSelected": true,
      "MaxFileSize": null,
      "OrdinalIndex": 0
    },
    {
      "Id": "4614379c-773e-4f94-8764-024c55b9b716",
      "Name": "UploadedAt",
      "Type": "DateTime",
      "EnumType": "",
      "EnumNamespace": "",
      "EnumAngularImport": "shared/enums",
      "EnumFilePath": null,
      "DefaultValue": null,
      "IsNullable": false,
      "IsRequired": false,
      "IsFilterable": true,
      "AllowEmptyStrings": false,
      "IsTextArea": false,
      "MinLength": null,
      "MaxLength": null,
      "SortOrder": 0,
      "SortType": 0,
      "Regex": "",
      "EmailValidation": false,
      "ShowOnList": true,
      "ShowOnCreateModal": true,
      "ShowOnEditModal": true,
      "ReadonlyOnEditModal": false,
      "EnumValues": null,
      "IsSelected": true,
      "MaxFileSize": null,
      "OrdinalIndex": 0
    }
  ],
  "NavigationProperties": [
    {
      "EntityNameWithDuplicationNumber": "Document",
      "EntitySetNameWithDuplicationNumber": "Documents",
      "ReferencePropertyName": "Document",
      "UiPickType": "Typeahead",
      "IsRequired": true,
      "IncludeEntitiesFromModules": false,
      "FromAbpModule": false,
      "Name": "DocumentId",
      "DisplayProperty": "Title",
      "Namespace": "HC.Documents",
      "EntityName": "Document",
      "EntitySetName": "Documents",
      "DtoNamespace": "HC.Documents",
      "DtoEntityName": "DocumentDto",
      "Type": "Guid",
      "IsFilterable": true
    }
  ],
  "NavigationConnections": [],
  "ChildEntities": [],
  "PhysicalFileName": "DocumentFile.json"
}