{
  "Id": "e01a38bf-8e1f-4887-b51a-0feb9bc9fb32",
  "Name": "Workflow",
  "OriginalName": "Workflow",
  "NamePlural": "Workflows",
  "DatabaseTableName": "Workflows",
  "Namespace": "Workflows",
  "Type": 1,
  "MasterEntityName": null,
  "MasterEntity": null,
  "BaseClass": "FullAuditedAggregateRoot",
  "PageTitle": "Workflows",
  "MenuIcon": "file-alt",
  "PrimaryKeyType": "Guid",
  "PreserveCustomCode": true,
  "IsMultiTenant": true,
  "CheckConcurrency": true,
  "BulkDeleteEnabled": true,
  "ShouldCreateUserInterface": true,
  "ShouldCreateBackend": true,
  "ShouldExportExcel": true,
  "ShouldAddMigration": true,
  "ShouldUpdateDatabase": true,
  "CreateTests": false,
  "Properties": [
    {
      "Id": "809e808f-ed5a-41e5-84bd-5045a8b20182",
      "Name": "Code",
      "Type": "string",
      "EnumType": "",
      "EnumNamespace": "",
      "EnumAngularImport": "shared/enums",
      "EnumFilePath": null,
      "DefaultValue": null,
      "IsNullable": false,
      "IsRequired": true,
      "IsFilterable": true,
      "AllowEmptyStrings": false,
      "IsTextArea": false,
      "MinLength": 1,
      "MaxLength": 50,
      "SortOrder": 0,
      "SortType": 0,
      "Regex": "",
      "EmailValidation": false,
      "ShowOnList": true,
      "ShowOnCreateModal": true,
      "ShowOnEditModal": true,
      "ReadonlyOnEditModal": false,
      "EnumValues": null,
      "IsSelected": true,
      "MaxFileSize": null,
      "OrdinalIndex": 0
    },
    {
      "Id": "333017a3-24d1-4f5c-bec5-e4379f84df20",
      "Name": "Name",
      "Type": "string",
      "EnumType": "",
      "EnumNamespace": "",
      "EnumAngularImport": "shared/enums",
      "EnumFilePath": null,
      "DefaultValue": null,
      "IsNullable": false,
      "IsRequired": true,
      "IsFilterable": true,
      "AllowEmptyStrings": false,
      "IsTextArea": false,
      "MinLength": null,
      "MaxLength": null,
      "SortOrder": 0,
      "SortType": 0,
      "Regex": "",
      "EmailValidation": false,
      "ShowOnList": true,
      "ShowOnCreateModal": true,
      "ShowOnEditModal": true,
      "ReadonlyOnEditModal": false,
      "EnumValues": null,
      "IsSelected": true,
      "MaxFileSize": null,
      "OrdinalIndex": 0
    },
    {
      "Id": "6cfdbd2f-04f9-4505-845f-ed764b76a469",
      "Name": "Description",
      "Type": "string",
      "EnumType": "",
      "EnumNamespace": "",
      "EnumAngularImport": "shared/enums",
      "EnumFilePath": null,
      "DefaultValue": null,
      "IsNullable": false,
      "IsRequired": false,
      "IsFilterable": true,
      "AllowEmptyStrings": false,
      "IsTextArea": true,
      "MinLength": null,
      "MaxLength": null,
      "SortOrder": 0,
      "SortType": 0,
      "Regex": "",
      "EmailValidation": false,
      "ShowOnList": true,
      "ShowOnCreateModal": true,
      "ShowOnEditModal": true,
      "ReadonlyOnEditModal": false,
      "EnumValues": null,
      "IsSelected": true,
      "MaxFileSize": null,
      "OrdinalIndex": 0
    },
    {
      "Id": "7c32d7fd-9ab0-46aa-9c22-7aa5d5c751ec",
      "Name": "IsActive",
      "Type": "bool",
      "EnumType": "",
      "EnumNamespace": "",
      "EnumAngularImport": "shared/enums",
      "EnumFilePath": null,
      "DefaultValue": "true",
      "IsNullable": false,
      "IsRequired": false,
      "IsFilterable": true,
      "AllowEmptyStrings": false,
      "IsTextArea": false,
      "MinLength": null,
      "MaxLength": null,
      "SortOrder": 0,
      "SortType": 0,
      "Regex": "",
      "EmailValidation": false,
      "ShowOnList": true,
      "ShowOnCreateModal": true,
      "ShowOnEditModal": true,
      "ReadonlyOnEditModal": false,
      "EnumValues": null,
      "IsSelected": true,
      "MaxFileSize": null,
      "OrdinalIndex": 0
    }
  ],
  "NavigationProperties": [
    {
      "EntityNameWithDuplicationNumber": "WorkflowDefinition",
      "EntitySetNameWithDuplicationNumber": "WorkflowDefinitions",
      "ReferencePropertyName": "WorkflowDefinition",
      "UiPickType": "Dropdown",
      "IsRequired": true,
      "IncludeEntitiesFromModules": false,
      "FromAbpModule": false,
      "Name": "WorkflowDefinitionId",
      "DisplayProperty": "Code",
      "Namespace": "HC.WorkflowDefinitions",
      "EntityName": "WorkflowDefinition",
      "EntitySetName": "WorkflowDefinitions",
      "DtoNamespace": "HC.WorkflowDefinitions",
      "DtoEntityName": "WorkflowDefinitionDto",
      "Type": "Guid",
      "IsFilterable": true
    }
  ],
  "NavigationConnections": [],
  "ChildEntities": [],
  "PhysicalFileName": "Workflow.json"
}